tests/__init__.py
tests/test_treehouse_draft.py
tests/test_files/p1_exists.png
tests/test_files/p_exists.png
tests/test_files/t1_exists.txt
tests/test_files/t_exists.txt
treehouse_design/__init__.py
treehouse_design/tree_species.txt
treehouse_design/treehouse_layout.py
treehouse_planner-0.0.2.dist-info/LICENSE
treehouse_planner-0.0.2.dist-info/METADATA
treehouse_planner-0.0.2.dist-info/WHEEL
treehouse_planner-0.0.2.dist-info/top_level.txt
treehouse_planner-0.0.2.dist-info/RECORD
