Metadata-Version: 2.1
Name: treehouse-planner
Version: 0.0.2
Summary: A drafting tool for treehouse construction
Author-email: Conner Wilson <cwilson022@icloud.com>
Project-URL: Homepage, https://github.com/cwilson-design/Treehouse-Planner
Classifier: Programming Language :: Python :: 3
Classifier: License :: OSI Approved :: MIT License
Classifier: Operating System :: OS Independent
Requires-Python: >=3.8
License-File: LICENSE
Requires-Dist: matplotlib >=3.9
Requires-Dist: matplotlib-inline
Requires-Dist: ipython
Requires-Dist: pytest
